wai_processing/__init__.py
wai_processing/paths.py
wai_processing/configs/rendering.yaml
wai_processing/configs/semantic_mapping.yaml
wai_processing/configs/colmap/default.yaml
wai_processing/configs/conversion/ase.yaml
wai_processing/configs/conversion/dioptra.yaml
wai_processing/configs/conversion/dl3dv.yaml
wai_processing/configs/conversion/eyeful_official_and_inofficial.yaml
wai_processing/configs/conversion/hyperscape.yaml
wai_processing/configs/conversion/re10k.yaml
wai_processing/configs/conversion/scannetppv2.yaml
wai_processing/configs/conversion/tartanair_v2.yaml
wai_processing/configs/conversion/tartanair_v2_minimal_example.yaml
wai_processing/configs/conversion/xrooms.yaml
wai_processing/configs/covisibility/covisibility_depth_iphone.yaml
wai_processing/configs/covisibility/covisibility_gt_depth.yaml
wai_processing/configs/covisibility/covisibility_gt_depth_224x224.yaml
wai_processing/configs/covisibility/covisibility_gt_depth_8x_downscale.yaml
wai_processing/configs/covisibility/covisibility_pred_depth.yaml
wai_processing/configs/covisibility/covisibility_pred_depth_224x224.yaml
wai_processing/configs/dashboard/default.yaml
wai_processing/configs/data_transfer/to_s3_default.yaml
wai_processing/configs/debug_visualize/debug_distorted.yaml
wai_processing/configs/debug_visualize/debug_undistort.yaml
wai_processing/configs/debug_visualize/debug_viz_final.yaml
wai_processing/configs/florence2/default.yaml
wai_processing/configs/launch/ase.yaml
wai_processing/configs/launch/dioptra.yaml
wai_processing/configs/launch/dl3dv.yaml
wai_processing/configs/launch/eyeful_official_and_inofficial.yaml
wai_processing/configs/launch/hyperscape.yaml
wai_processing/configs/launch/re10k.yaml
wai_processing/configs/launch/scannetppv2.yaml
wai_processing/configs/launch/tartanair_v2.yaml
wai_processing/configs/launch/xrooms.yaml
wai_processing/configs/launch/dryrun/ase.yaml
wai_processing/configs/launch/dryrun/dioptra.yaml
wai_processing/configs/launch/dryrun/dl3dv.yaml
wai_processing-0.9.dist-info/METADATA
wai_processing-0.9.dist-info/WHEEL
wai_processing-0.9.dist-info/entry_points.txt
wai_processing-0.9.dist-info/top_level.txt
wai_processing-0.9.dist-info/RECORD
