Metadata-Version: 2.4
Name: wai-processing
Version: 0.9
Summary: Processing suite for the WorldAI Format (WAI)
Author-email: Norman Mueller <normanm@meta.com>
Requires-Python: >=3.8.0
Requires-Dist: wai-core
Requires-Dist: trimesh
Requires-Dist: open3d
Requires-Dist: pyrender
Requires-Dist: ninja
Requires-Dist: nvdiffrast
Requires-Dist: cython
Requires-Dist: tqdm
Requires-Dist: pyyaml
Requires-Dist: argconf
Provides-Extra: aria
Requires-Dist: projectaria-tools[all]; extra == "aria"
Provides-Extra: tartanair
Requires-Dist: tartanair; extra == "tartanair"
Provides-Extra: mast3r
Requires-Dist: numpy==1.26.4; extra == "mast3r"
Provides-Extra: metric3dv2
Requires-Dist: HTML4Vision; extra == "metric3dv2"
Requires-Dist: timm; extra == "metric3dv2"
Requires-Dist: tensorboardX; extra == "metric3dv2"
Requires-Dist: mmcv; extra == "metric3dv2"
Provides-Extra: florence2
Requires-Dist: transformers==4.46.3; extra == "florence2"
Requires-Dist: timm; extra == "florence2"
Provides-Extra: profiling
Requires-Dist: bson; extra == "profiling"
Requires-Dist: orjson; extra == "profiling"
Requires-Dist: oyaml; extra == "profiling"
Requires-Dist: openexr; extra == "profiling"
Requires-Dist: ruamel.yaml; extra == "profiling"
Provides-Extra: dashboard
Requires-Dist: fastapi; extra == "dashboard"
Requires-Dist: plotly; extra == "dashboard"
Requires-Dist: polars; extra == "dashboard"
Requires-Dist: uvicorn; extra == "dashboard"
Requires-Dist: aiosqlite; extra == "dashboard"
Requires-Dist: pydantic; extra == "dashboard"
Provides-Extra: viz
Requires-Dist: rerun-sdk; extra == "viz"
Provides-Extra: colormap
Requires-Dist: colour-science; extra == "colormap"
Provides-Extra: s3
Requires-Dist: aioboto3; extra == "s3"
Requires-Dist: tenacity; extra == "s3"
Provides-Extra: dev
Requires-Dist: pytest; extra == "dev"
Requires-Dist: pytest-cov; extra == "dev"
Requires-Dist: pre-commit; extra == "dev"
Requires-Dist: ruff; extra == "dev"
Requires-Dist: imageio; extra == "dev"
Provides-Extra: all
Requires-Dist: wai-processing[aria]; extra == "all"
Requires-Dist: wai-processing[tartanair]; extra == "all"
Requires-Dist: wai-processing[mast3r]; extra == "all"
Requires-Dist: wai-processing[metric3dv2]; extra == "all"
Requires-Dist: wai-processing[florence2]; extra == "all"
Requires-Dist: wai-processing[profiling]; extra == "all"
Requires-Dist: wai-processing[dashboard]; extra == "all"
Requires-Dist: wai-processing[viz]; extra == "all"
Requires-Dist: wai-processing[colormap]; extra == "all"
Requires-Dist: wai-processing[s3]; extra == "all"
Requires-Dist: wai-processing[dev]; extra == "all"
